{
	"__credit": "Generated using Animated Java (https://animated-java.dev/)",
	"textures": {
		"1": "minecraft:item/enemy/abyss/base"
	},
	"elements": [
		{
			"faces": {
				"north": {"uv": [0, 0, 8, 8], "texture": "#1"},
				"east": {"uv": [0, 0, 8, 8], "texture": "#1"},
				"south": {"uv": [0, 0, 8, 8], "texture": "#1"},
				"west": {"uv": [0, 0, 8, 8], "texture": "#1"},
				"up": {"uv": [0, 0, 8, 8], "texture": "#1"},
				"down": {"uv": [0, 0, 8, 8], "texture": "#1"}
			},
			"to": [17.84, 11.48, 20.9],
			"from": [9.2, 5, -4.9],
			"rotation": {"angle": 0, "axis": "y", "origin": [8, 4.76, 7.88]}
		}
	],
	"display": {
		"head": {
			"translation": [0, 5.6, 0],
			"scale": [4, 4, 4],
			"rotation": [0, 0, 0]
		}
	}
}